pyspritelib/__init__.py
pyspritelib/spritesheet.py
pyspritelib-1.0.dist-info/METADATA
pyspritelib-1.0.dist-info/WHEEL
pyspritelib-1.0.dist-info/top_level.txt
pyspritelib-1.0.dist-info/RECORD
