Metadata-Version: 2.1
Name: pyspritelib
Version: 1.0
Summary: pygame spritesheet simplifier
Home-page: https://github.com/QZ-K/pysprite-lib
Author: QZ
Author-email: kuzeykural040510@gmail.com
Classifier: Programming Language :: Python :: 3
Classifier: License :: OSI Approved :: MIT License
Classifier: Operating System :: OS Independent
Requires-Python: >=3.6
Requires-Dist: pygame
